LICENSE
MANIFEST.in
README.md
pyproject.toml
setup.py
./sparse_dot_topn_for_blocks/array_wrappers.pyx
./sparse_dot_topn_for_blocks/sparse_dot_topn.pyx
./sparse_dot_topn_for_blocks/sparse_dot_topn_parallel.cpp
./sparse_dot_topn_for_blocks/sparse_dot_topn_source.cpp
./sparse_dot_topn_for_blocks/sparse_dot_topn_threaded.pyx
sparse_dot_topn_for_blocks/__init__.py
sparse_dot_topn_for_blocks/array_wrappers.pxd
sparse_dot_topn_for_blocks/array_wrappers.pyx
sparse_dot_topn_for_blocks/awesome_cossim_topn.py
sparse_dot_topn_for_blocks/sparse_dot_topn.pyx
sparse_dot_topn_for_blocks/sparse_dot_topn_parallel.cpp
sparse_dot_topn_for_blocks/sparse_dot_topn_parallel.h
sparse_dot_topn_for_blocks/sparse_dot_topn_source.cpp
sparse_dot_topn_for_blocks/sparse_dot_topn_source.h
sparse_dot_topn_for_blocks/sparse_dot_topn_threaded.pyx
sparse_dot_topn_for_blocks.egg-info/PKG-INFO
sparse_dot_topn_for_blocks.egg-info/SOURCES.txt
sparse_dot_topn_for_blocks.egg-info/dependency_links.txt
sparse_dot_topn_for_blocks.egg-info/not-zip-safe
sparse_dot_topn_for_blocks.egg-info/requires.txt
sparse_dot_topn_for_blocks.egg-info/top_level.txt