Metadata-Version: 2.1
Name: sparse-dot-topn-for-blocks
Version: 0.3.1.post1
Summary: This package is intended for matrix blocks, boosting a sparse matrix multiplication followed by selecting the top-n multiplication
Home-page: https://github.com/ParticularMiner/sparse_dot_topn_for_blocks
Author: Particular Miner
Author-email: particularminer@fake.com
License: Apache 2.0
Keywords: cosine-similarity sparse-matrix scipy cython
Platform: UNKNOWN
